CHANGELOG.rst
INSTALL.rst
MANIFEST.in
README.rst
setup.cfg
setup.py
src/kids/__init__.py
src/kids.ansi.egg-info/PKG-INFO
src/kids.ansi.egg-info/SOURCES.txt
src/kids.ansi.egg-info/dependency_links.txt
src/kids.ansi.egg-info/requires.txt
src/kids.ansi.egg-info/top_level.txt
src/kids/ansi/__init__.py
src/kids/ansi/ansi.py