Metadata-Version: 1.1
Name: kids.ansi
Version: 0.0.1
Summary: Kids python ANSI string library
Home-page: http://github.com/0k/kids.ansi
Author: Valentin LAB
Author-email: valentin.lab@kalysto.org
License: UNKNOWN
Platform: UNKNOWN
Classifier: Programming Language :: Python
Classifier: Topic :: Software Development :: Libraries :: Python Modules
Classifier: Development Status :: 3 - Alpha
Classifier: License :: OSI Approved :: BSD License
Classifier: Topic :: Software Development
Classifier: Intended Audience :: Developers
